overpass/__init__.py
overpass/api.py
overpass/errors.py
overpass/queries.py
overpass/utils.py
overpass-0.7.1.dist-info/LICENSE.txt
overpass-0.7.1.dist-info/METADATA
overpass-0.7.1.dist-info/WHEEL
overpass-0.7.1.dist-info/RECORD
