Metadata-Version: 2.1
Name: overpass
Version: 0.7.1
Summary: A Python interface to the OpenStreetMap Overpass API
License: MIT
Author: Martijn van Exel
Author-email: m@rtijn.org
Requires-Python: >3.9,<3.12
Classifier: License :: OSI Approved :: MIT License
Classifier: Programming Language :: Python :: 3
Classifier: Programming Language :: Python :: 3.10
Classifier: Programming Language :: Python :: 3.11
Requires-Dist: osm2geojson (>=0.2.5,<0.3.0)
Requires-Dist: requests (>=2.32.3,<3.0.0)
